pyswcloader/__init__.py
pyswcloader/brain.py
pyswcloader/cluster.py
pyswcloader/distance.py
pyswcloader/io.py
pyswcloader/projection.py
pyswcloader/projection_batch.py
pyswcloader/swc.py
pyswcloader/visualization.py
pyswcloader/database/acro_stl_dict.pkl
pyswcloader/database/allen_brain_tree.pkl
pyswcloader/database/stl_acro_dict.pkl
pyswcloader-1.1.1.dist-info/LICENSE.txt
pyswcloader-1.1.1.dist-info/METADATA
pyswcloader-1.1.1.dist-info/WHEEL
pyswcloader-1.1.1.dist-info/top_level.txt
pyswcloader-1.1.1.dist-info/RECORD
